odoo/addons/mrp_planned_order_matrix/README.rst
odoo/addons/mrp_planned_order_matrix/__init__.py
odoo/addons/mrp_planned_order_matrix/__manifest__.py
odoo/addons/mrp_planned_order_matrix/i18n/mrp_planned_order_matrix.pot
odoo/addons/mrp_planned_order_matrix/readme/CONTRIBUTORS.rst
odoo/addons/mrp_planned_order_matrix/readme/DESCRIPTION.rst
odoo/addons/mrp_planned_order_matrix/readme/INSTALL.rst
odoo/addons/mrp_planned_order_matrix/readme/USAGE.rst
odoo/addons/mrp_planned_order_matrix/security/ir.model.access.csv
odoo/addons/mrp_planned_order_matrix/static/description/icon.png
odoo/addons/mrp_planned_order_matrix/static/description/index.html
odoo/addons/mrp_planned_order_matrix/tests/__init__.py
odoo/addons/mrp_planned_order_matrix/tests/test_mrp_planned_order_matrix.py
odoo/addons/mrp_planned_order_matrix/wizards/__init__.py
odoo/addons/mrp_planned_order_matrix/wizards/mrp_planned_order_wizard.py
odoo/addons/mrp_planned_order_matrix/wizards/mrp_planned_order_wizard_view.xml
odoo14_addon_mrp_planned_order_matrix-14.0.1.1.0.dist-info/METADATA
odoo14_addon_mrp_planned_order_matrix-14.0.1.1.0.dist-info/WHEEL
odoo14_addon_mrp_planned_order_matrix-14.0.1.1.0.dist-info/top_level.txt
odoo14_addon_mrp_planned_order_matrix-14.0.1.1.0.dist-info/RECORD
