Metadata-Version: 2.1
Name: odoo14-addon-mrp-planned-order-matrix
Version: 14.0.1.1.0
Summary: Allows to create fixed planned orders on a grid view.
Home-page: https://github.com/OCA/manufacture
Author: ForgeFlow, Odoo Community Association (OCA)
Author-email: support@odoo-community.org
License: AGPL-3
Platform: UNKNOWN
Classifier: Programming Language :: Python
Classifier: Framework :: Odoo
Classifier: Framework :: Odoo :: 14.0
Classifier: License :: OSI Approved :: GNU Affero General Public License v3
Requires-Python: >=3.6
Requires-Dist: odoo14-addon-date-range
Requires-Dist: odoo14-addon-mrp-multi-level
Requires-Dist: odoo14-addon-web-widget-x2many-2d-matrix
Requires-Dist: odoo (<14.1dev,>=14.0a)
